<Properties>
  <MonoDevelop.Ide.Workbench>
    <Pads>
      <Pad Id="ProjectPad">
        <State name="__root__">
          <Node name="Assembly-CSharp-Editor" expanded="True">
            <Node name="Assembly-CSharp-Editor" expanded="True">
              <Node name="Assets" expanded="True">
                <Node name="TDS" expanded="True">
                  <Node name="Script" expanded="True">
                    <Node name="Editor" expanded="True">
                      <Node name="TDSIOSBuildPostProcessor.cs" selected="True" />
                    </Node>
                  </Node>
                </Node>
              </Node>
            </Node>
          </Node>
        </State>
      </Pad>
    </Pads>
  </MonoDevelop.Ide.Workbench>
  <MonoDevelop.Ide.DebuggingService.PinnedWatches />
  <MonoDevelop.Ide.Workspace ActiveConfiguration="Debug" />
  <MonoDevelop.Ide.DebuggingService.Breakpoints>
    <BreakpointStore />
  </MonoDevelop.Ide.DebuggingService.Breakpoints>
  <MultiItemStartupConfigurations />
</Properties>